[
  {"question":"What was the name of the angel who appeared to Mary?","optionA":"Michael","optionB":"Raphael","optionC":"Gabriel","optionD":"Uriel","correctAnswer":"C","explanation":"Luke 1:26-27 — God sent the angel Gabriel to a virgin named Mary.","book":"Luke","round":"Round 2 — Gospels & Acts","bank":"B"},
  {"question":"What does 'Immanuel' mean?","optionA":"Savior of the world","optionB":"God with us","optionC":"Prince of Peace","optionD":"Lord of Lords","correctAnswer":"B","explanation":"Matthew 1:23 — 'Immanuel,' which is translated, 'God with us.'","book":"Matthew","round":"Round 2 — Gospels & Acts","bank":"B"},
  {"question":"Who was the governor who condemned Jesus to death?","optionA":"Herod","optionB":"Caiaphas","optionC":"Pontius Pilate","optionD":"Caesar","correctAnswer":"C","explanation":"Matthew 27:26 — Pontius Pilate released Barabbas and had Jesus scourged and handed over to be crucified.","book":"Matthew","round":"Round 2 — Gospels & Acts","bank":"B"},
  {"question":"What were the first words of Jesus's public ministry according to Matthew?","optionA":"Repent and be baptized","optionB":"Love one another","optionC":"Repent, for the kingdom of heaven is at hand","optionD":"Follow me","correctAnswer":"C","explanation":"Matthew 4:17 — Jesus began to preach: 'Repent, for the kingdom of heaven is at hand.'","book":"Matthew","round":"Round 2 — Gospels & Acts","bank":"B"},
  {"question":"Who wrote the Gospel of Luke?","optionA":"Mark","optionB":"Luke the physician","optionC":"Paul","optionD":"Peter","correctAnswer":"B","explanation":"Colossians 4:14 identifies Luke as a physician; the early church consistently attributed this Gospel to him.","book":"Luke","round":"Round 2 — Gospels & Acts","bank":"B"},
  {"question":"What did the prodigal son ask his father for?","optionA":"Forgiveness","optionB":"His share of the inheritance","optionC":"A servant's job","optionD":"A new robe","correctAnswer":"B","explanation":"Luke 15:12 — The younger son asked for his share of the property, and the father divided it.","book":"Luke","round":"Round 2 — Gospels & Acts","bank":"B"},
  {"question":"Who said 'In the beginning was the Word'?","optionA":"Matthew","optionB":"Paul","optionC":"John","optionD":"Peter","correctAnswer":"C","explanation":"John 1:1 — The opening of John's Gospel: 'In the beginning was the Word, and the Word was with God.'","book":"John","round":"Round 2 — Gospels & Acts","bank":"B"},
  {"question":"What did Jesus say He is in John 11:25?","optionA":"The Way, Truth, and Life","optionB":"The Resurrection and the Life","optionC":"The Door","optionD":"The Good Shepherd","correctAnswer":"B","explanation":"John 11:25 — 'I am the resurrection and the life. He who believes in Me, though he may die, he shall live.'","book":"John","round":"Round 2 — Gospels & Acts","bank":"B"},
  {"question":"Who was the disciple Jesus loved, according to John's Gospel?","optionA":"Peter","optionB":"Matthew","optionC":"John","optionD":"Lazarus","correctAnswer":"C","explanation":"John 13:23 — 'One of His disciples, whom Jesus loved, was reclining at table at Jesus' side.'","book":"John","round":"Round 2 — Gospels & Acts","bank":"B"},
  {"question":"What is the shortest verse in the Bible?","optionA":"God is love","optionB":"Jesus wept","optionC":"Pray always","optionD":"Fear not","correctAnswer":"B","explanation":"John 11:35 — 'Jesus wept.' This is the shortest verse in the English Bible.","book":"John","round":"Round 2 — Gospels & Acts","bank":"B"},
  {"question":"Who replaced Judas Iscariot among the twelve?","optionA":"Paul","optionB":"Stephen","optionC":"Matthias","optionD":"Barnabas","correctAnswer":"C","explanation":"Acts 1:26 — They cast their lots, and the lot fell on Matthias, and he was numbered with the eleven apostles.","book":"Acts","round":"Round 2 — Gospels & Acts","bank":"B"},
  {"question":"In Acts, who was the apostle to the Gentiles?","optionA":"Peter","optionB":"John","optionC":"Paul","optionD":"James","correctAnswer":"C","explanation":"Acts 9:15 — God told Ananias that Paul was 'a chosen vessel to bear My name before Gentiles.'","book":"Acts","round":"Round 2 — Gospels & Acts","bank":"B"},
  {"question":"Where was Paul when he first heard the Macedonian call?","optionA":"Antioch","optionB":"Troas","optionC":"Ephesus","optionD":"Athens","correctAnswer":"B","explanation":"Acts 16:8-9 — Paul had a vision at Troas: a man of Macedonia begging him to come over and help.","book":"Acts","round":"Round 2 — Gospels & Acts","bank":"B"},
  {"question":"What city did Paul preach in when he spoke on Mars Hill?","optionA":"Corinth","optionB":"Rome","optionC":"Athens","optionD":"Thessalonica","correctAnswer":"C","explanation":"Acts 17:22 — Paul stood in the midst of the Areopagus in Athens and preached.","book":"Acts","round":"Round 2 — Gospels & Acts","bank":"B"},
  {"question":"What river did Naomi and Ruth walk toward when returning to Bethlehem?","optionA":"Nile","optionB":"Euphrates","optionC":"Jordan","optionD":"Tigris","correctAnswer":"C","explanation":"Ruth 1:22 — They returned from Moab and arrived in Bethlehem, crossing through the Jordan region.","book":"Ruth","round":"Round 1 — History","bank":"B"},
  {"question":"Who was the mother of Samuel the prophet?","optionA":"Naomi","optionB":"Ruth","optionC":"Hannah","optionD":"Peninnah","correctAnswer":"C","explanation":"1 Samuel 1:20 — Hannah conceived and bore a son and called his name Samuel.","book":"1 Samuel","round":"Round 1 — History","bank":"B"},
  {"question":"What gift did Hannah promise God in exchange for a son?","optionA":"A tithe of all she had","optionB":"To dedicate the child to the LORD all his life","optionC":"To build an altar","optionD":"To never eat meat","correctAnswer":"B","explanation":"1 Samuel 1:11 — Hannah vowed to give the child to the LORD all the days of his life.","book":"1 Samuel","round":"Round 1 — History","bank":"B"},
  {"question":"Who secretly anointed David as king in Bethlehem?","optionA":"Nathan","optionB":"Eli","optionC":"Samuel","optionD":"Gad","correctAnswer":"C","explanation":"1 Samuel 16:13 — Samuel took the horn of oil and anointed David in the midst of his brothers.","book":"1 Samuel","round":"Round 1 — History","bank":"B"},
  {"question":"What instrument did David play to soothe Saul's troubled spirit?","optionA":"Flute","optionB":"Trumpet","optionC":"Harp","optionD":"Lyre","correctAnswer":"C","explanation":"1 Samuel 16:23 — David played the harp whenever the harmful spirit was upon Saul.","book":"1 Samuel","round":"Round 1 — History","bank":"B"},
  {"question":"How many stones did David pick up to face Goliath?","optionA":"1","optionB":"3","optionC":"5","optionD":"7","correctAnswer":"C","explanation":"1 Samuel 17:40 — David chose five smooth stones from the brook and put them in his shepherd's bag.","book":"1 Samuel","round":"Round 1 — History","bank":"B"},
  {"question":"What did Moses's rod turn into when thrown before Pharaoh?","optionA":"A lion","optionB":"A serpent","optionC":"A tree","optionD":"A stone","correctAnswer":"B","explanation":"Exodus 7:10 — Aaron threw down his rod before Pharaoh and it became a serpent.","book":"Exodus","round":"Round 1 — History","bank":"B"},
  {"question":"How many plagues did God send on Egypt?","optionA":"7","optionB":"8","optionC":"10","optionD":"12","correctAnswer":"C","explanation":"Exodus chapters 7-12 record ten plagues God sent upon Egypt.","book":"Exodus","round":"Round 1 — History","bank":"B"},
  {"question":"What was the first plague God sent on Egypt?","optionA":"Locusts","optionB":"Frogs","optionC":"Blood","optionD":"Darkness","correctAnswer":"C","explanation":"Exodus 7:20-21 — Moses struck the Nile waters and they turned to blood.","book":"Exodus","round":"Round 1 — History","bank":"B"},
  {"question":"What did the Israelites put on their doorposts during Passover?","optionA":"Oil","optionB":"Blood of a lamb","optionC":"Water","optionD":"Salt","correctAnswer":"B","explanation":"Exodus 12:7 — They put the blood on the doorposts so the destroyer would pass over their houses.","book":"Exodus","round":"Round 1 — History","bank":"B"},
  {"question":"What body of water did God part for the Israelites to escape Pharaoh?","optionA":"Jordan River","optionB":"Red Sea","optionC":"Nile River","optionD":"Mediterranean Sea","correctAnswer":"B","explanation":"Exodus 14:21-22 — Moses stretched out his hand and the LORD drove the sea back, making dry land.","book":"Exodus","round":"Round 1 — History","bank":"B"},
  {"question":"True or False: In Titus 1, an overseer must be blameless and the husband of one wife.","optionA":"True","optionB":"False","optionC":"Only for deacons","optionD":"Not found in Titus","correctAnswer":"A","explanation":"Titus 1:6 — 'If a man is blameless, the husband of one wife, having faithful children...'","book":"Titus","round":"Round 3 — Epistles","bank":"B"},
  {"question":"According to James 1:2, how should we count various trials?","optionA":"As punishment","optionB":"As all joy","optionC":"As tests to avoid","optionD":"As God's absence","correctAnswer":"B","explanation":"James 1:2 — 'My brethren, count it all joy when you fall into various trials.'","book":"James","round":"Round 3 — Epistles","bank":"B"},
  {"question":"True or False: 1 Peter 5:8 compares the devil to a roaring lion.","optionA":"True","optionB":"False","optionC":"It compares the devil to a serpent","optionD":"Only in a footnote","correctAnswer":"A","explanation":"1 Peter 5:8 — 'Be sober, be vigilant; because your adversary the devil walks about like a roaring lion.'","book":"1 Peter","round":"Round 3 — Epistles","bank":"B"},
  {"question":"According to 2 Peter 3:9, why does God delay His return?","optionA":"He is judging angels first","optionB":"He is not willing that any should perish","optionC":"He is waiting for the temple to be rebuilt","optionD":"He is waiting for 1,000 converts","correctAnswer":"B","explanation":"2 Peter 3:9 — 'The Lord is not slack... but is longsuffering toward us, not willing that any should perish.'","book":"2 Peter","round":"Round 3 — Epistles","bank":"B"},
  {"question":"In Ephesians 4, what is the purpose of the gifts Christ gave the church?","optionA":"To compete with other churches","optionB":"To equip the saints for the work of ministry","optionC":"To perform miracles only","optionD":"To collect offerings","correctAnswer":"B","explanation":"Ephesians 4:12 — Gifts were given 'for the equipping of the saints for the work of ministry.'","book":"Ephesians","round":"Round 3 — Epistles","bank":"B"},
  {"question":"What is the 'sword of the Spirit' according to Ephesians 6?","optionA":"Prayer","optionB":"Faith","optionC":"The word of God","optionD":"Praise","correctAnswer":"C","explanation":"Ephesians 6:17 — 'Take... the sword of the Spirit, which is the word of God.'","book":"Ephesians","round":"Round 3 — Epistles","bank":"B"},
  {"question":"What tribe of Israel did Paul belong to?","optionA":"Judah","optionB":"Levi","optionC":"Benjamin","optionD":"Dan","correctAnswer":"C","explanation":"Philippians 3:5 — Paul identified himself as of the tribe of Benjamin.","book":"Acts","round":"Round 4 — Doctrine","bank":"B"},
  {"question":"What does 'gospel' literally mean?","optionA":"Holy book","optionB":"Good news","optionC":"God's law","optionD":"Sacred text","correctAnswer":"B","explanation":"The Greek word 'euangelion' means good news — the good news of Jesus Christ.","book":"Mark","round":"Round 4 — Doctrine","bank":"B"},
  {"question":"What doctrine teaches that Jesus is both fully God and fully man?","optionA":"Modalism","optionB":"Hypostatic union","optionC":"Arianism","optionD":"Gnosticism","correctAnswer":"B","explanation":"The hypostatic union is the doctrine that Jesus Christ is one person with two natures: divine and human.","book":"John","round":"Round 4 — Doctrine","bank":"B"},
  {"question":"According to Ephesians 2:8, salvation is a gift of whom?","optionA":"The church","optionB":"The prophets","optionC":"God","optionD":"The Holy Spirit alone","correctAnswer":"C","explanation":"Ephesians 2:8 — 'For by grace you have been saved through faith, and that not of yourselves; it is the gift of God.'","book":"Ephesians","round":"Round 4 — Doctrine","bank":"B"},
  {"question":"Who wrote the book of Acts?","optionA":"Paul","optionB":"Luke","optionC":"John","optionD":"Peter","correctAnswer":"B","explanation":"The book of Acts is addressed to Theophilus (Acts 1:1), the same recipient as Luke's Gospel, indicating Luke as the author.","book":"Acts","round":"Round 4 — Doctrine","bank":"B"},
  {"question":"Which book begins: 'The beginning of the gospel of Jesus Christ, the Son of God'?","optionA":"Matthew","optionB":"Luke","optionC":"John","optionD":"Mark","correctAnswer":"D","explanation":"Mark 1:1 — 'The beginning of the gospel of Jesus Christ, the Son of God.'","book":"Mark","round":"Round 2 — Gospels & Acts","bank":"B"},
  {"question":"According to John 3:16, what did God give because He loved the world?","optionA":"The Law","optionB":"Eternal life directly","optionC":"His only begotten Son","optionD":"The prophets","correctAnswer":"C","explanation":"John 3:16 — 'For God so loved the world that He gave His only begotten Son.'","book":"John","round":"Round 2 — Gospels & Acts","bank":"B"},
  {"question":"Who was Nicodemus in the Gospel of John?","optionA":"A Pharisee and ruler of the Jews","optionB":"A tax collector","optionC":"A Samaritan","optionD":"A fisherman","correctAnswer":"A","explanation":"John 3:1 — There was a man of the Pharisees named Nicodemus, a ruler of the Jews.","book":"John","round":"Round 2 — Gospels & Acts","bank":"B"},
  {"question":"Who was the woman at the well Jesus spoke to in John 4?","optionA":"A Jewish widow","optionB":"A Samaritan woman","optionC":"Mary Magdalene","optionD":"Martha","correctAnswer":"B","explanation":"John 4:7-9 — A woman of Samaria came to draw water and Jesus spoke with her.","book":"John","round":"Round 2 — Gospels & Acts","bank":"B"}
]
